pub_sub/__init__.py
pub_sub/dependecies.py
pub_sub/pub_sub.py
pub_sub/rmq_adapter.py
pub_sub/schemas.py
easy_rmq-0.1.0.dist-info/METADATA
easy_rmq-0.1.0.dist-info/WHEEL
easy_rmq-0.1.0.dist-info/RECORD
